eagle/__init__.py
resnet/__init__.py
resnet/convert_image_to_tfrecod.py
resnet/nsfw_main_finetune.py
resnet/nsfw_scratch.py
resnet/resnet_model.py
resnet/resnet_run_loop.py
resnet/utils/__init__.py
resnet/utils/accelerator/__init__.py
resnet/utils/accelerator/tpu.py
resnet/utils/accelerator/tpu_test.py
resnet/utils/data/__init__.py
resnet/utils/data/file_io.py
resnet/utils/data/file_io_test.py
resnet/utils/export/__init__.py
resnet/utils/export/export.py
resnet/utils/export/export_test.py
resnet/utils/flags/__init__.py
resnet/utils/flags/_base.py
resnet/utils/flags/_benchmark.py
resnet/utils/flags/_conventions.py
resnet/utils/flags/_device.py
resnet/utils/flags/_misc.py
resnet/utils/flags/_performance.py
resnet/utils/flags/core.py
resnet/utils/flags/flags_test.py
resnet/utils/logs/__init__.py
resnet/utils/logs/cloud_lib.py
resnet/utils/logs/cloud_lib_test.py
resnet/utils/logs/hooks.py
resnet/utils/logs/hooks_helper.py
resnet/utils/logs/hooks_helper_test.py
resnet/utils/logs/hooks_test.py
resnet/utils/logs/logger.py
resnet/utils/logs/logger_test.py
resnet/utils/logs/metric_hook.py
resnet/utils/logs/metric_hook_test.py
resnet/utils/misc/__init__.py
resnet/utils/misc/distribution_utils.py
resnet/utils/misc/distribution_utils_test.py
resnet/utils/misc/model_helpers.py
resnet/utils/misc/model_helpers_test.py
resnet/utils/testing/__init__.py
resnet/utils/testing/integration.py
resnet/utils/testing/mock_lib.py
resnet/utils/testing/reference_data.py
resnet/utils/testing/reference_data_test.py
rsnsfw/__init__.py
rsnsfw-0.0.6.dist-info/LICENSE
rsnsfw-0.0.6.dist-info/METADATA
rsnsfw-0.0.6.dist-info/WHEEL
rsnsfw-0.0.6.dist-info/top_level.txt
rsnsfw-0.0.6.dist-info/RECORD
